pdf_compress/__init__.py
pdf_compress-0.1.0.dist-info/entry_points.txt
pdf_compress-0.1.0.dist-info/LICENSE
pdf_compress-0.1.0.dist-info/WHEEL
pdf_compress-0.1.0.dist-info/METADATA
pdf_compress-0.1.0.dist-info/RECORD
